davidsousa/__init__.py
davidsousa/email_utils.py
davidsousa-0.3.0.dist-info/LICENSE
davidsousa-0.3.0.dist-info/METADATA
davidsousa-0.3.0.dist-info/WHEEL
davidsousa-0.3.0.dist-info/top_level.txt
davidsousa-0.3.0.dist-info/RECORD
