Metadata-Version: 2.1
Name: davidsousa
Version: 0.3.0
Summary: Biblioteca para envio de e-mails com suporte a HTML e prioridade (Experimental). (Gmail)
Home-page: https://github.com/davidsousadev/davidsousa
Author: David Sousa
Author-email: davidffsousaff@gmail.com
Keywords: email gmail smtp sending
Classifier: Programming Language :: Python :: 3
Classifier: License :: OSI Approved :: MIT License
Classifier: Operating System :: OS Independent
Requires-Python: >=3.6
License-File: LICENSE
Requires-Dist: secure-smtplib
